setup.cfg
setup.py
isocountrycode/__init__.py
isocountrycode/alpha2.py
isocountrycode.egg-info/PKG-INFO
isocountrycode.egg-info/SOURCES.txt
isocountrycode.egg-info/dependency_links.txt
isocountrycode.egg-info/not-zip-safe
isocountrycode.egg-info/requires.txt
isocountrycode.egg-info/top_level.txt